{"cameraMode":{"drawMode":0,"name":"Shaded","section":"Shading Mode"},"sceneLighting":true,"audioPlay":false,"sceneViewState":{"m_AlwaysRefresh":false,"showFog":true,"showSkybox":true,"showFlares":true,"showImageEffects":true,"showParticleSystems":true,"showVisualEffectGraphs":true,"m_FxEnabled":true},"in2DMode":false,"pivot":{"x":3.4552292823791506,"y":-2.0234274864196779,"z":-3.588789939880371},"rotation":{"x":0.09665808081626892,"y":0.8296142220497131,"z":-0.1517496258020401,"w":0.5286043286323547},"size":9.816948890686036,"orthographic":true}